inavmspapi/__init__.py
inavmspapi/msp_codes.py
inavmspapi/transmitter.py
inavmspapi/utils.py
inavmspapi-1.1.0.dist-info/METADATA
inavmspapi-1.1.0.dist-info/WHEEL
inavmspapi-1.1.0.dist-info/top_level.txt
inavmspapi-1.1.0.dist-info/RECORD
