Metadata-Version: 2.4
Name: inavmspapi
Version: 1.1.0
Summary: This module allows you to implement the transmitter logic for MSP
Author-email: AgroTechAvia <example@main.com>
License-Expression: Apache-2.0
Classifier: Programming Language :: Python :: 3
Classifier: Operating System :: OS Independent
Requires-Python: >=3.10
Requires-Dist: pynput
Requires-Dist: pyserial
Requires-Dist: future
Requires-Dist: iso8601
Requires-Dist: pyYAML
